mlalchemy/__init__.py
mlalchemy/constants.py
mlalchemy/errors.py
mlalchemy/parser.py
mlalchemy/structures.py
mlalchemy/testing.py
mlalchemy/utils.py
mlalchemy-0.2.2.dist-info/DESCRIPTION.rst
mlalchemy-0.2.2.dist-info/METADATA
mlalchemy-0.2.2.dist-info/RECORD
mlalchemy-0.2.2.dist-info/WHEEL
mlalchemy-0.2.2.dist-info/metadata.json
mlalchemy-0.2.2.dist-info/top_level.txt
