Metadata-Version: 1.1
Name: mlalchemy
Version: 0.2.2
Summary: Library for converting YAML/JSON to SQLAlchemy SELECT queries
Home-page: https://github.com/thanethomson/MLAlchemy
Author: Thane Thomson
Author-email: connect@thanethomson.com
License: MIT
Platform: UNKNOWN
Classifier: Development Status :: 4 - Beta
Classifier: Intended Audience :: Developers
Classifier: License :: OSI Approved :: MIT License
Classifier: Natural Language :: English
Classifier: Operating System :: POSIX
Classifier: Operating System :: MacOS
Classifier: Programming Language :: Python :: 2.7
Classifier: Programming Language :: Python :: 3.5
Classifier: Programming Language :: Python :: 3.6
Classifier: Topic :: Database
Classifier: Topic :: Utilities
Classifier: Topic :: Software Development :: Libraries
